pelican_flickrtag/__init__.py
pelican_flickrtag/flickr.py
pelican_flickrtag/plugin.py
pelican_flickrtag-0.6.0.dist-info/DESCRIPTION.rst
pelican_flickrtag-0.6.0.dist-info/METADATA
pelican_flickrtag-0.6.0.dist-info/RECORD
pelican_flickrtag-0.6.0.dist-info/WHEEL
pelican_flickrtag-0.6.0.dist-info/metadata.json
pelican_flickrtag-0.6.0.dist-info/top_level.txt
