Metadata-Version: 2.0
Name: pelican-flickrtag
Version: 0.6.0
Summary: Display Flickr images easily in your Pelican articles.
Home-page: https://github.com/streeter/pelican-flickrtag
Author: Chris Streeter
Author-email: chris@chrisstreeter.com
License: MIT
Platform: UNKNOWN
Classifier: Operating System :: OS Independent
Classifier: Programming Language :: Python
Classifier: Programming Language :: Python :: 2.6
Classifier: Programming Language :: Python :: 2.7
Classifier: Programming Language :: Python :: 3.5
Classifier: Programming Language :: Python :: 3.6
Classifier: Topic :: Internet :: WWW/HTTP
Classifier: Topic :: Software Development :: Libraries :: Python Modules
Classifier: Topic :: Text Processing
Requires-Dist: jinja2
Requires-Dist: pelican
